README.rst
aiohttp_negotiate.py
setup.py
aiohttp_negotiate.egg-info/PKG-INFO
aiohttp_negotiate.egg-info/SOURCES.txt
aiohttp_negotiate.egg-info/dependency_links.txt
aiohttp_negotiate.egg-info/pbr.json
aiohttp_negotiate.egg-info/requires.txt
aiohttp_negotiate.egg-info/top_level.txt