Metadata-Version: 1.0
Name: aiohttp-negotiate
Version: 0.9.2
Summary: Mixin for Negotiate authentication for aiohttp
Home-page: https://github.com/ox-it/aiohttp-negotiate
Author: IT Services, University of Oxford
Author-email: github@it.ox.ac.uk
License: BSD
Platform: UNKNOWN
